{
  "tickerInfo": {
    "티커": "IWMY",
    "운용사": "Defiance",
    "지급주기": "Weekly",
    "52 Week Range": "$21.84 - $43.50",
    "Volume": "162,734",
    "Avg. Volume": "90,680",
    "NAV": "$24.30",
    "Yield": "98.58%",
    "YTD Daily Total Return": "-71.84%"
  },
  "dividendHistory": [
    {
      "배당락일": "07/03/2025",
      "배당금": "$0.2410",
      "배당락전일종가": "$24.23",
      "배당락일종가": "$24.38"
    },
    {
      "배당락일": "06/26/2025",
      "배당금": "$0.2400",
      "배당락전일종가": "$23.56",
      "배당락일종가": "$23.72"
    },
    {
      "배당락일": "06/18/2025",
      "배당금": "$0.2380",
      "배당락전일종가": "$23.21",
      "배당락일종가": "$23.43"
    },
    {
      "배당락일": "06/12/2025",
      "배당금": "$0.2410",
      "배당락전일종가": "$23.54",
      "배당락일종가": "$23.54"
    },
    {
      "배당락일": "06/05/2025",
      "배당금": "$0.2380",
      "배당락전일종가": "$22.90",
      "배당락일종가": "$22.93"
    },
    {
      "배당락일": "05/29/2025",
      "배당금": "$0.2380",
      "배당락전일종가": "$22.52",
      "배당락일종가": "$22.63"
    },
    {
      "배당락일": "05/22/2025",
      "배당금": "$0.2460",
      "배당락전일종가": "$22.36",
      "배당락일종가": "$22.42"
    },
    {
      "배당락일": "05/15/2025",
      "배당금": "$0.2410",
      "배당락전일종가": "$22.65",
      "배당락일종가": "$22.82"
    },
    {
      "배당락일": "05/08/2025",
      "배당금": "$0.2420",
      "배당락전일종가": "$22.05",
      "배당락일종가": "$22.25"
    },
    {
      "배당락일": "05/01/2025",
      "배당금": "$0.2350",
      "배당락전일종가": "$21.65",
      "배당락일종가": "$21.66"
    },
    {
      "배당락일": "04/24/2025",
      "배당금": "$0.3370",
      "배당락전일종가": "$20.87",
      "배당락일종가": "$21.20"
    },
    {
      "배당락일": "04/17/2025",
      "배당금": "$0.3310",
      "배당락전일종가": "$20.63",
      "배당락일종가": "$20.75"
    },
    {
      "배당락일": "04/10/2025",
      "배당금": "$0.2800",
      "배당락전일종가": "$20.44",
      "배당락일종가": "$19.63"
    },
    {
      "배당락일": "04/03/2025",
      "배당금": "$0.3100",
      "배당락전일종가": "$22.44",
      "배당락일종가": "$21.03"
    },
    {
      "배당락일": "03/27/2025",
      "배당금": "$0.3210",
      "배당락전일종가": "$22.60",
      "배당락일종가": "$22.59"
    },
    {
      "배당락일": "03/20/2025",
      "배당금": "$0.3210",
      "배당락전일종가": "$22.81",
      "배당락일종가": "$22.76"
    },
    {
      "배당락일": "03/13/2025",
      "배당금": "$0.3290",
      "배당락전일종가": "$22.39",
      "배당락일종가": "$22.23"
    },
    {
      "배당락일": "03/06/2025",
      "배당금": "$0.2830",
      "배당락전일종가": "$22.69",
      "배당락일종가": "$22.46"
    },
    {
      "배당락일": "02/27/2025",
      "배당금": "$0.2570",
      "배당락전일종가": "$23.30",
      "배당락일종가": "$22.95"
    },
    {
      "배당락일": "02/20/2025",
      "배당금": "$0.2690",
      "배당락전일종가": "$24.09",
      "배당락일종가": "$23.95"
    },
    {
      "배당락일": "02/13/2025",
      "배당금": "$0.2990",
      "배당락전일종가": "$23.81",
      "배당락일종가": "$23.98"
    },
    {
      "배당락일": "02/06/2025",
      "배당금": "$0.3010",
      "배당락전일종가": "$24.02",
      "배당락일종가": "$23.97"
    },
    {
      "배당락일": "01/30/2025",
      "배당금": "$0.1040",
      "배당락전일종가": "$23.77",
      "배당락일종가": "$23.88"
    },
    {
      "배당락일": "01/23/2025",
      "배당금": "$0.3020",
      "배당락전일종가": "$23.85",
      "배당락일종가": "$23.94"
    }
  ]
}