{
  "tickerInfo": {
    "name": "TQQY",
    "fullname": "GraniteShares YieldBOOST QQQ ETF",
    "company": "GraniteShares",
    "frequency": "Weekly",
    "group": "목요일",
    "Update": "2025-07-10 12:17:09 KST",
    "52Week": "$17.64 - $25.38",
    "Volume": "7,904",
    "AvgVolume": "7,523",
    "NAV": "$18.88",
    "Yield": "N/A",
    "TotalReturn": "N/A"
  },
  "dividendHistory": [
    {
      "배당락일": "25. 07. 03",
      "배당금": "$0.1800",
      "배당락전일종가": "$19.01",
      "배당락일종가": "$19.09"
    },
    {
      "배당락일": "25. 06. 27",
      "배당금": "$0.1810",
      "배당락전일종가": "$18.72",
      "배당락일종가": "$18.75"
    },
    {
      "배당락일": "25. 06. 20",
      "배당금": "$0.1780",
      "배당락전일종가": "$18.35",
      "배당락일종가": "$18.38"
    },
    {
      "배당락일": "25. 06. 13",
      "배당금": "$0.1820",
      "배당락전일종가": "$18.50",
      "배당락일종가": "$18.22"
    },
    {
      "배당락일": "25. 06. 06",
      "배당금": "$0.1800",
      "배당락전일종가": "$18.04",
      "배당락일종가": "$18.16"
    },
    {
      "배당락일": "25. 05. 23",
      "배당금": "$0.7710",
      "배당락전일종가": "$17.63",
      "배당락일종가": "$17.12"
    },
    {
      "배당락일": "25. 04. 25",
      "배당금": "$0.7500",
      "배당락전일종가": "$16.56",
      "배당락일종가": "$16.58"
    },
    {
      "배당락일": "25. 03. 28",
      "배당금": "$1.0000",
      "배당락전일종가": "$18.59",
      "배당락일종가": "$17.43"
    }
  ]
}